scanline.py
scanline-0.2.1.dist-info/DESCRIPTION.rst
scanline-0.2.1.dist-info/METADATA
scanline-0.2.1.dist-info/RECORD
scanline-0.2.1.dist-info/WHEEL
scanline-0.2.1.dist-info/entry_points.txt
scanline-0.2.1.dist-info/metadata.json
scanline-0.2.1.dist-info/top_level.txt
