Metadata-Version: 2.0
Name: scanline
Version: 0.2.1
Summary: Script for extraction of attitudes from 3d models using meshlab's point picking tool
Home-page: https://github.com/endarthur/scanline
Author: Arthur Endlein
Author-email: endarthur@gmail.com
License: MIT
Keywords: geology attitudes meshlab
Platform: UNKNOWN
Classifier: Development Status :: 3 - Alpha
Classifier: Topic :: Utilities
Classifier: License :: OSI Approved :: MIT License
Requires-Dist: numpy
